{"juz": 17, "page_number": 334, "data": [{"chapter_id": 22, "chapter_arab": "\u0627\u0644\u062d\u062c", "chapter_bismillah_pre": true, "chapter_indo": "Haji", "have_first_ayat": false, "lines": [[{"id": 18495, "position": 1, "line_number": 1, "text": "\ufb51", "char_type_name": "word", "verse_id": 2611, "verse_number": 16}, {"id": 18496, "position": 2, "line_number": 1, "text": "\ufb52", "char_type_name": "word", "verse_id": 2611, "verse_number": 16}, {"id": 18497, "position": 3, "line_number": 1, "text": "\ufb53", "char_type_name": "word", "verse_id": 2611, "verse_number": 16}, {"id": 18498, "position": 4, "line_number": 1, "text": "\ufb54", "char_type_name": "word", "verse_id": 2611, "verse_number": 16}, {"id": 18499, "position": 5, "line_number": 1, "text": "\ufb55", "char_type_name": "word", "verse_id": 2611, "verse_number": 16}, {"id": 18500, "position": 6, "line_number": 1, "text": "\ufb56", "char_type_name": "word", "verse_id": 2611, "verse_number": 16}, {"id": 18501, "position": 7, "line_number": 1, "text": "\ufb57", "char_type_name": "word", "verse_id": 2611, "verse_number": 16}, {"id": 18502, "position": 8, "line_number": 1, "text": "\ufb58", "char_type_name": "word", "verse_id": 2611, "verse_number": 16}, {"id": 18503, "position": 9, "line_number": 1, "text": "\ufb59", "char_type_name": "word", "verse_id": 2611, "verse_number": 16}], [{"id": 18504, "position": 10, "line_number": 2, "text": "\ufb5a", "char_type_name": "end", "verse_id": 2611, "verse_number": 16}, {"id": 19469, "position": 1, "line_number": 2, "text": "\ufb5b", "char_type_name": "word", "verse_id": 2612, "verse_number": 17}, {"id": 19470, "position": 2, "line_number": 2, "text": "\ufb5c", "char_type_name": "word", "verse_id": 2612, "verse_number": 17}, {"id": 19471, "position": 3, "line_number": 2, "text": "\ufb5d", "char_type_name": "word", "verse_id": 2612, "verse_number": 17}, {"id": 19472, "position": 4, "line_number": 2, "text": "\ufb5e", "char_type_name": "word", "verse_id": 2612, "verse_number": 17}, {"id": 19473, "position": 5, "line_number": 2, "text": "\ufb5f", "char_type_name": "word", "verse_id": 2612, "verse_number": 17}, {"id": 19474, "position": 6, "line_number": 2, "text": "\ufb60", "char_type_name": "word", "verse_id": 2612, "verse_number": 17}, {"id": 19475, "position": 7, "line_number": 2, "text": "\ufb61", "char_type_name": "word", "verse_id": 2612, "verse_number": 17}], [{"id": 19476, "position": 8, "line_number": 3, "text": "\ufb62", "char_type_name": "word", "verse_id": 2612, "verse_number": 17}, {"id": 19477, "position": 9, "line_number": 3, "text": "\ufb63", "char_type_name": "word", "verse_id": 2612, "verse_number": 17}, {"id": 19478, "position": 10, "line_number": 3, "text": "\ufb64", "char_type_name": "word", "verse_id": 2612, "verse_number": 17}, {"id": 19479, "position": 11, "line_number": 3, "text": "\ufb65", "char_type_name": "word", "verse_id": 2612, "verse_number": 17}, {"id": 19480, "position": 12, "line_number": 3, "text": "\ufb66", "char_type_name": "word", "verse_id": 2612, "verse_number": 17}, {"id": 19481, "position": 13, "line_number": 3, "text": "\ufb67", "char_type_name": "word", "verse_id": 2612, "verse_number": 17}, {"id": 19482, "position": 14, "line_number": 3, "text": "\ufb68", "char_type_name": "word", "verse_id": 2612, "verse_number": 17}], [{"id": 19483, "position": 15, "line_number": 4, "text": "\ufb69", "char_type_name": "word", "verse_id": 2612, "verse_number": 17}, {"id": 19484, "position": 16, "line_number": 4, "text": "\ufb6a\ufb6b", "char_type_name": "word", "verse_id": 2612, "verse_number": 17}, {"id": 19486, "position": 17, "line_number": 4, "text": "\ufb6c", "char_type_name": "word", "verse_id": 2612, "verse_number": 17}, {"id": 19487, "position": 18, "line_number": 4, "text": "\ufb6d", "char_type_name": "word", "verse_id": 2612, "verse_number": 17}, {"id": 19488, "position": 19, "line_number": 4, "text": "\ufb6e", "char_type_name": "word", "verse_id": 2612, "verse_number": 17}, {"id": 19489, "position": 20, "line_number": 4, "text": "\ufb6f", "char_type_name": "word", "verse_id": 2612, "verse_number": 17}, {"id": 19490, "position": 21, "line_number": 4, "text": "\ufb70", "char_type_name": "word", "verse_id": 2612, "verse_number": 17}, {"id": 19491, "position": 22, "line_number": 4, "text": "\ufb71", "char_type_name": "word", "verse_id": 2612, "verse_number": 17}, {"id": 19492, "position": 23, "line_number": 4, "text": "\ufb72", "char_type_name": "end", "verse_id": 2612, "verse_number": 17}, {"id": 20551, "position": 1, "line_number": 4, "text": "\ufb73", "char_type_name": "word", "verse_id": 2613, "verse_number": 18}, {"id": 20552, "position": 2, "line_number": 4, "text": "\ufb74", "char_type_name": "word", "verse_id": 2613, "verse_number": 18}, {"id": 20553, "position": 3, "line_number": 4, "text": "\ufb75", "char_type_name": "word", "verse_id": 2613, "verse_number": 18}, {"id": 20554, "position": 4, "line_number": 4, "text": "\ufb76", "char_type_name": "word", "verse_id": 2613, "verse_number": 18}], [{"id": 20555, "position": 5, "line_number": 5, "text": "\ufb77", "char_type_name": "word", "verse_id": 2613, "verse_number": 18}, {"id": 20556, "position": 6, "line_number": 5, "text": "\ufb78", "char_type_name": "word", "verse_id": 2613, "verse_number": 18}, {"id": 20557, "position": 7, "line_number": 5, "text": "\ufb79", "char_type_name": "word", "verse_id": 2613, "verse_number": 18}, {"id": 20558, "position": 8, "line_number": 5, "text": "\ufb7a", "char_type_name": "word", "verse_id": 2613, "verse_number": 18}, {"id": 20559, "position": 9, "line_number": 5, "text": "\ufb7b", "char_type_name": "word", "verse_id": 2613, "verse_number": 18}, {"id": 20560, "position": 10, "line_number": 5, "text": "\ufb7c", "char_type_name": "word", "verse_id": 2613, "verse_number": 18}, {"id": 20561, "position": 11, "line_number": 5, "text": "\ufb7d", "char_type_name": "word", "verse_id": 2613, "verse_number": 18}, {"id": 20562, "position": 12, "line_number": 5, "text": "\ufb7e", "char_type_name": "word", "verse_id": 2613, "verse_number": 18}, {"id": 20563, "position": 13, "line_number": 5, "text": "\ufb7f", "char_type_name": "word", "verse_id": 2613, "verse_number": 18}, {"id": 20564, "position": 14, "line_number": 5, "text": "\ufb80", "char_type_name": "word", "verse_id": 2613, "verse_number": 18}], [{"id": 20565, "position": 15, "line_number": 6, "text": "\ufb81", "char_type_name": "word", "verse_id": 2613, "verse_number": 18}, {"id": 20566, "position": 16, "line_number": 6, "text": "\ufb82", "char_type_name": "word", "verse_id": 2613, "verse_number": 18}, {"id": 20567, "position": 17, "line_number": 6, "text": "\ufb83", "char_type_name": "word", "verse_id": 2613, "verse_number": 18}, {"id": 20568, "position": 18, "line_number": 6, "text": "\ufb84", "char_type_name": "word", "verse_id": 2613, "verse_number": 18}, {"id": 20569, "position": 19, "line_number": 6, "text": "\ufb85", "char_type_name": "word", "verse_id": 2613, "verse_number": 18}, {"id": 20570, "position": 20, "line_number": 6, "text": "\ufb86", "char_type_name": "word", "verse_id": 2613, "verse_number": 18}, {"id": 20571, "position": 21, "line_number": 6, "text": "\ufb87\ufb88", "char_type_name": "word", "verse_id": 2613, "verse_number": 18}], [{"id": 20573, "position": 22, "line_number": 7, "text": "\ufb89", "char_type_name": "word", "verse_id": 2613, "verse_number": 18}, {"id": 20574, "position": 23, "line_number": 7, "text": "\ufb8a", "char_type_name": "word", "verse_id": 2613, "verse_number": 18}, {"id": 20575, "position": 24, "line_number": 7, "text": "\ufb8b", "char_type_name": "word", "verse_id": 2613, "verse_number": 18}, {"id": 20576, "position": 25, "line_number": 7, "text": "\ufb8c\ufb8d", "char_type_name": "word", "verse_id": 2613, "verse_number": 18}, {"id": 20578, "position": 26, "line_number": 7, "text": "\ufb8e", "char_type_name": "word", "verse_id": 2613, "verse_number": 18}, {"id": 20579, "position": 27, "line_number": 7, "text": "\ufb8f", "char_type_name": "word", "verse_id": 2613, "verse_number": 18}, {"id": 20580, "position": 28, "line_number": 7, "text": "\ufb90", "char_type_name": "word", "verse_id": 2613, "verse_number": 18}, {"id": 20581, "position": 29, "line_number": 7, "text": "\ufb91", "char_type_name": "word", "verse_id": 2613, "verse_number": 18}, {"id": 20582, "position": 30, "line_number": 7, "text": "\ufb92", "char_type_name": "word", "verse_id": 2613, "verse_number": 18}, {"id": 20583, "position": 31, "line_number": 7, "text": "\ufb93", "char_type_name": "word", "verse_id": 2613, "verse_number": 18}, {"id": 20584, "position": 32, "line_number": 7, "text": "\ufb94\ufb95", "char_type_name": "word", "verse_id": 2613, "verse_number": 18}], [{"id": 20586, "position": 33, "line_number": 8, "text": "\ufb96", "char_type_name": "word", "verse_id": 2613, "verse_number": 18}, {"id": 20587, "position": 34, "line_number": 8, "text": "\ufb97", "char_type_name": "word", "verse_id": 2613, "verse_number": 18}, {"id": 20588, "position": 35, "line_number": 8, "text": "\ufb98", "char_type_name": "word", "verse_id": 2613, "verse_number": 18}, {"id": 20589, "position": 36, "line_number": 8, "text": "\ufb99", "char_type_name": "word", "verse_id": 2613, "verse_number": 18}, {"id": 20590, "position": 37, "line_number": 8, "text": "\ufb9a\ufb9b", "char_type_name": "word", "verse_id": 2613, "verse_number": 18}, {"id": 20592, "position": 38, "line_number": 8, "text": "\ufb9c", "char_type_name": "end", "verse_id": 2613, "verse_number": 18}, {"id": 21636, "position": 1, "line_number": 8, "text": "\ufb9d \ufb9e", "char_type_name": "word", "verse_id": 2614, "verse_number": 19}, {"id": 21637, "position": 2, "line_number": 8, "text": "\ufb9f", "char_type_name": "word", "verse_id": 2614, "verse_number": 19}, {"id": 21638, "position": 3, "line_number": 8, "text": "\ufba0", "char_type_name": "word", "verse_id": 2614, "verse_number": 19}], [{"id": 21639, "position": 4, "line_number": 9, "text": "\ufba1", "char_type_name": "word", "verse_id": 2614, "verse_number": 19}, {"id": 21640, "position": 5, "line_number": 9, "text": "\ufba2\ufba3", "char_type_name": "word", "verse_id": 2614, "verse_number": 19}, {"id": 21642, "position": 6, "line_number": 9, "text": "\ufba4", "char_type_name": "word", "verse_id": 2614, "verse_number": 19}, {"id": 21643, "position": 7, "line_number": 9, "text": "\ufba5", "char_type_name": "word", "verse_id": 2614, "verse_number": 19}, {"id": 21644, "position": 8, "line_number": 9, "text": "\ufba6", "char_type_name": "word", "verse_id": 2614, "verse_number": 19}, {"id": 21645, "position": 9, "line_number": 9, "text": "\ufba7", "char_type_name": "word", "verse_id": 2614, "verse_number": 19}, {"id": 21646, "position": 10, "line_number": 9, "text": "\ufba8", "char_type_name": "word", "verse_id": 2614, "verse_number": 19}, {"id": 21647, "position": 11, "line_number": 9, "text": "\ufba9", "char_type_name": "word", "verse_id": 2614, "verse_number": 19}, {"id": 21648, "position": 12, "line_number": 9, "text": "\ufbaa", "char_type_name": "word", "verse_id": 2614, "verse_number": 19}, {"id": 21649, "position": 13, "line_number": 9, "text": "\ufbab", "char_type_name": "word", "verse_id": 2614, "verse_number": 19}], [{"id": 21650, "position": 14, "line_number": 10, "text": "\ufbac", "char_type_name": "word", "verse_id": 2614, "verse_number": 19}, {"id": 21651, "position": 15, "line_number": 10, "text": "\ufbad", "char_type_name": "word", "verse_id": 2614, "verse_number": 19}, {"id": 21652, "position": 16, "line_number": 10, "text": "\ufbae", "char_type_name": "word", "verse_id": 2614, "verse_number": 19}, {"id": 21653, "position": 17, "line_number": 10, "text": "\ufbaf", "char_type_name": "word", "verse_id": 2614, "verse_number": 19}, {"id": 21654, "position": 18, "line_number": 10, "text": "\ufbb0", "char_type_name": "end", "verse_id": 2614, "verse_number": 19}, {"id": 22733, "position": 1, "line_number": 10, "text": "\ufbb1", "char_type_name": "word", "verse_id": 2615, "verse_number": 20}, {"id": 22734, "position": 2, "line_number": 10, "text": "\ufbd3", "char_type_name": "word", "verse_id": 2615, "verse_number": 20}, {"id": 22735, "position": 3, "line_number": 10, "text": "\ufbd4", "char_type_name": "word", "verse_id": 2615, "verse_number": 20}, {"id": 22736, "position": 4, "line_number": 10, "text": "\ufbd5", "char_type_name": "word", "verse_id": 2615, "verse_number": 20}, {"id": 22737, "position": 5, "line_number": 10, "text": "\ufbd6", "char_type_name": "word", "verse_id": 2615, "verse_number": 20}], [{"id": 22738, "position": 6, "line_number": 11, "text": "\ufbd7", "char_type_name": "word", "verse_id": 2615, "verse_number": 20}, {"id": 22739, "position": 7, "line_number": 11, "text": "\ufbd8", "char_type_name": "end", "verse_id": 2615, "verse_number": 20}, {"id": 23886, "position": 1, "line_number": 11, "text": "\ufbd9", "char_type_name": "word", "verse_id": 2616, "verse_number": 21}, {"id": 23887, "position": 2, "line_number": 11, "text": "\ufbda", "char_type_name": "word", "verse_id": 2616, "verse_number": 21}, {"id": 23888, "position": 3, "line_number": 11, "text": "\ufbdb", "char_type_name": "word", "verse_id": 2616, "verse_number": 21}, {"id": 23889, "position": 4, "line_number": 11, "text": "\ufbdc", "char_type_name": "word", "verse_id": 2616, "verse_number": 21}, {"id": 23890, "position": 5, "line_number": 11, "text": "\ufbdd", "char_type_name": "end", "verse_id": 2616, "verse_number": 21}, {"id": 24888, "position": 1, "line_number": 11, "text": "\ufbde", "char_type_name": "word", "verse_id": 2617, "verse_number": 22}, {"id": 24889, "position": 2, "line_number": 11, "text": "\ufbdf", "char_type_name": "word", "verse_id": 2617, "verse_number": 22}], [{"id": 24890, "position": 3, "line_number": 12, "text": "\ufbe0", "char_type_name": "word", "verse_id": 2617, "verse_number": 22}, {"id": 24891, "position": 4, "line_number": 12, "text": "\ufbe1", "char_type_name": "word", "verse_id": 2617, "verse_number": 22}, {"id": 24892, "position": 5, "line_number": 12, "text": "\ufbe2", "char_type_name": "word", "verse_id": 2617, "verse_number": 22}, {"id": 24893, "position": 6, "line_number": 12, "text": "\ufbe3", "char_type_name": "word", "verse_id": 2617, "verse_number": 22}, {"id": 24894, "position": 7, "line_number": 12, "text": "\ufbe4", "char_type_name": "word", "verse_id": 2617, "verse_number": 22}, {"id": 24895, "position": 8, "line_number": 12, "text": "\ufbe5", "char_type_name": "word", "verse_id": 2617, "verse_number": 22}, {"id": 24896, "position": 9, "line_number": 12, "text": "\ufbe6", "char_type_name": "word", "verse_id": 2617, "verse_number": 22}, {"id": 24897, "position": 10, "line_number": 12, "text": "\ufbe7", "char_type_name": "word", "verse_id": 2617, "verse_number": 22}, {"id": 24898, "position": 11, "line_number": 12, "text": "\ufbe8", "char_type_name": "word", "verse_id": 2617, "verse_number": 22}, {"id": 24899, "position": 12, "line_number": 12, "text": "\ufbe9", "char_type_name": "word", "verse_id": 2617, "verse_number": 22}], [{"id": 24900, "position": 13, "line_number": 13, "text": "\ufbea", "char_type_name": "end", "verse_id": 2617, "verse_number": 22}, {"id": 25946, "position": 1, "line_number": 13, "text": "\ufbeb", "char_type_name": "word", "verse_id": 2618, "verse_number": 23}, {"id": 25947, "position": 2, "line_number": 13, "text": "\ufbec", "char_type_name": "word", "verse_id": 2618, "verse_number": 23}, {"id": 25948, "position": 3, "line_number": 13, "text": "\ufbed", "char_type_name": "word", "verse_id": 2618, "verse_number": 23}, {"id": 25949, "position": 4, "line_number": 13, "text": "\ufbee", "char_type_name": "word", "verse_id": 2618, "verse_number": 23}, {"id": 25950, "position": 5, "line_number": 13, "text": "\ufbef", "char_type_name": "word", "verse_id": 2618, "verse_number": 23}, {"id": 25951, "position": 6, "line_number": 13, "text": "\ufbf0", "char_type_name": "word", "verse_id": 2618, "verse_number": 23}, {"id": 25952, "position": 7, "line_number": 13, "text": "\ufbf1", "char_type_name": "word", "verse_id": 2618, "verse_number": 23}], [{"id": 25953, "position": 8, "line_number": 14, "text": "\ufbf2", "char_type_name": "word", "verse_id": 2618, "verse_number": 23}, {"id": 25954, "position": 9, "line_number": 14, "text": "\ufbf3", "char_type_name": "word", "verse_id": 2618, "verse_number": 23}, {"id": 25955, "position": 10, "line_number": 14, "text": "\ufbf4", "char_type_name": "word", "verse_id": 2618, "verse_number": 23}, {"id": 25956, "position": 11, "line_number": 14, "text": "\ufbf5", "char_type_name": "word", "verse_id": 2618, "verse_number": 23}, {"id": 25957, "position": 12, "line_number": 14, "text": "\ufbf6", "char_type_name": "word", "verse_id": 2618, "verse_number": 23}, {"id": 25958, "position": 13, "line_number": 14, "text": "\ufbf7", "char_type_name": "word", "verse_id": 2618, "verse_number": 23}, {"id": 25959, "position": 14, "line_number": 14, "text": "\ufbf8", "char_type_name": "word", "verse_id": 2618, "verse_number": 23}, {"id": 25960, "position": 15, "line_number": 14, "text": "\ufbf9", "char_type_name": "word", "verse_id": 2618, "verse_number": 23}], [{"id": 25961, "position": 16, "line_number": 15, "text": "\ufbfa", "char_type_name": "word", "verse_id": 2618, "verse_number": 23}, {"id": 25962, "position": 17, "line_number": 15, "text": "\ufbfb", "char_type_name": "word", "verse_id": 2618, "verse_number": 23}, {"id": 25963, "position": 18, "line_number": 15, "text": "\ufbfc", "char_type_name": "word", "verse_id": 2618, "verse_number": 23}, {"id": 25964, "position": 19, "line_number": 15, "text": "\ufbfd\ufbfe", "char_type_name": "word", "verse_id": 2618, "verse_number": 23}, {"id": 25966, "position": 20, "line_number": 15, "text": "\ufbff", "char_type_name": "word", "verse_id": 2618, "verse_number": 23}, {"id": 25967, "position": 21, "line_number": 15, "text": "\ufc00", "char_type_name": "word", "verse_id": 2618, "verse_number": 23}, {"id": 25968, "position": 22, "line_number": 15, "text": "\ufc01", "char_type_name": "word", "verse_id": 2618, "verse_number": 23}, {"id": 25969, "position": 23, "line_number": 15, "text": "\ufc02", "char_type_name": "end", "verse_id": 2618, "verse_number": 23}]]}]}