{"juz": 14, "page_number": 268, "data": [{"chapter_id": 16, "chapter_arab": "\u0627\u0644\u0646\u062d\u0644", "chapter_bismillah_pre": true, "chapter_indo": "Lebah Madu", "have_first_ayat": false, "lines": [[{"id": 8395, "position": 1, "line_number": 1, "text": "\ufb51", "char_type_name": "word", "verse_id": 1908, "verse_number": 7}, {"id": 8396, "position": 2, "line_number": 1, "text": "\ufb52", "char_type_name": "word", "verse_id": 1908, "verse_number": 7}, {"id": 8397, "position": 3, "line_number": 1, "text": "\ufb53", "char_type_name": "word", "verse_id": 1908, "verse_number": 7}, {"id": 8398, "position": 4, "line_number": 1, "text": "\ufb54", "char_type_name": "word", "verse_id": 1908, "verse_number": 7}, {"id": 8399, "position": 5, "line_number": 1, "text": "\ufb55", "char_type_name": "word", "verse_id": 1908, "verse_number": 7}, {"id": 8400, "position": 6, "line_number": 1, "text": "\ufb56", "char_type_name": "word", "verse_id": 1908, "verse_number": 7}, {"id": 8401, "position": 7, "line_number": 1, "text": "\ufb57", "char_type_name": "word", "verse_id": 1908, "verse_number": 7}, {"id": 8402, "position": 8, "line_number": 1, "text": "\ufb58", "char_type_name": "word", "verse_id": 1908, "verse_number": 7}, {"id": 8403, "position": 9, "line_number": 1, "text": "\ufb59", "char_type_name": "word", "verse_id": 1908, "verse_number": 7}], [{"id": 8404, "position": 10, "line_number": 2, "text": "\ufb5a\ufb5b", "char_type_name": "word", "verse_id": 1908, "verse_number": 7}, {"id": 8406, "position": 11, "line_number": 2, "text": "\ufb5c", "char_type_name": "word", "verse_id": 1908, "verse_number": 7}, {"id": 8407, "position": 12, "line_number": 2, "text": "\ufb5d", "char_type_name": "word", "verse_id": 1908, "verse_number": 7}, {"id": 8408, "position": 13, "line_number": 2, "text": "\ufb5e", "char_type_name": "word", "verse_id": 1908, "verse_number": 7}, {"id": 8409, "position": 14, "line_number": 2, "text": "\ufb5f", "char_type_name": "word", "verse_id": 1908, "verse_number": 7}, {"id": 8410, "position": 15, "line_number": 2, "text": "\ufb60", "char_type_name": "end", "verse_id": 1908, "verse_number": 7}, {"id": 9587, "position": 1, "line_number": 2, "text": "\ufb61", "char_type_name": "word", "verse_id": 1909, "verse_number": 8}, {"id": 9588, "position": 2, "line_number": 2, "text": "\ufb62", "char_type_name": "word", "verse_id": 1909, "verse_number": 8}], [{"id": 9589, "position": 3, "line_number": 3, "text": "\ufb63", "char_type_name": "word", "verse_id": 1909, "verse_number": 8}, {"id": 9590, "position": 4, "line_number": 3, "text": "\ufb64", "char_type_name": "word", "verse_id": 1909, "verse_number": 8}, {"id": 9591, "position": 5, "line_number": 3, "text": "\ufb65\ufb66", "char_type_name": "word", "verse_id": 1909, "verse_number": 8}, {"id": 9593, "position": 6, "line_number": 3, "text": "\ufb67", "char_type_name": "word", "verse_id": 1909, "verse_number": 8}, {"id": 9594, "position": 7, "line_number": 3, "text": "\ufb68", "char_type_name": "word", "verse_id": 1909, "verse_number": 8}, {"id": 9595, "position": 8, "line_number": 3, "text": "\ufb69", "char_type_name": "word", "verse_id": 1909, "verse_number": 8}, {"id": 9596, "position": 9, "line_number": 3, "text": "\ufb6a", "char_type_name": "word", "verse_id": 1909, "verse_number": 8}, {"id": 9597, "position": 10, "line_number": 3, "text": "\ufb6b", "char_type_name": "end", "verse_id": 1909, "verse_number": 8}], [{"id": 10760, "position": 1, "line_number": 4, "text": "\ufb6c", "char_type_name": "word", "verse_id": 1910, "verse_number": 9}, {"id": 10761, "position": 2, "line_number": 4, "text": "\ufb6d", "char_type_name": "word", "verse_id": 1910, "verse_number": 9}, {"id": 10762, "position": 3, "line_number": 4, "text": "\ufb6e", "char_type_name": "word", "verse_id": 1910, "verse_number": 9}, {"id": 10763, "position": 4, "line_number": 4, "text": "\ufb6f", "char_type_name": "word", "verse_id": 1910, "verse_number": 9}, {"id": 10764, "position": 5, "line_number": 4, "text": "\ufb70", "char_type_name": "word", "verse_id": 1910, "verse_number": 9}, {"id": 10765, "position": 6, "line_number": 4, "text": "\ufb71\ufb72", "char_type_name": "word", "verse_id": 1910, "verse_number": 9}, {"id": 10767, "position": 7, "line_number": 4, "text": "\ufb73", "char_type_name": "word", "verse_id": 1910, "verse_number": 9}, {"id": 10768, "position": 8, "line_number": 4, "text": "\ufb74", "char_type_name": "word", "verse_id": 1910, "verse_number": 9}, {"id": 10769, "position": 9, "line_number": 4, "text": "\ufb75", "char_type_name": "word", "verse_id": 1910, "verse_number": 9}], [{"id": 10770, "position": 10, "line_number": 5, "text": "\ufb76", "char_type_name": "word", "verse_id": 1910, "verse_number": 9}, {"id": 10771, "position": 11, "line_number": 5, "text": "\ufb77", "char_type_name": "end", "verse_id": 1910, "verse_number": 9}, {"id": 12011, "position": 1, "line_number": 5, "text": "\ufb78", "char_type_name": "word", "verse_id": 1911, "verse_number": 10}, {"id": 12012, "position": 2, "line_number": 5, "text": "\ufb79", "char_type_name": "word", "verse_id": 1911, "verse_number": 10}, {"id": 12013, "position": 3, "line_number": 5, "text": "\ufb7a", "char_type_name": "word", "verse_id": 1911, "verse_number": 10}, {"id": 12014, "position": 4, "line_number": 5, "text": "\ufb7b", "char_type_name": "word", "verse_id": 1911, "verse_number": 10}, {"id": 12015, "position": 5, "line_number": 5, "text": "\ufb7c", "char_type_name": "word", "verse_id": 1911, "verse_number": 10}, {"id": 12016, "position": 6, "line_number": 5, "text": "\ufb7d\ufb7e", "char_type_name": "word", "verse_id": 1911, "verse_number": 10}, {"id": 12018, "position": 7, "line_number": 5, "text": "\ufb7f", "char_type_name": "word", "verse_id": 1911, "verse_number": 10}, {"id": 12019, "position": 8, "line_number": 5, "text": "\ufb80", "char_type_name": "word", "verse_id": 1911, "verse_number": 10}], [{"id": 12020, "position": 9, "line_number": 6, "text": "\ufb81", "char_type_name": "word", "verse_id": 1911, "verse_number": 10}, {"id": 12021, "position": 10, "line_number": 6, "text": "\ufb82", "char_type_name": "word", "verse_id": 1911, "verse_number": 10}, {"id": 12022, "position": 11, "line_number": 6, "text": "\ufb83", "char_type_name": "word", "verse_id": 1911, "verse_number": 10}, {"id": 12023, "position": 12, "line_number": 6, "text": "\ufb84", "char_type_name": "word", "verse_id": 1911, "verse_number": 10}, {"id": 12024, "position": 13, "line_number": 6, "text": "\ufb85", "char_type_name": "word", "verse_id": 1911, "verse_number": 10}, {"id": 12025, "position": 14, "line_number": 6, "text": "\ufb86", "char_type_name": "end", "verse_id": 1911, "verse_number": 10}, {"id": 13332, "position": 1, "line_number": 6, "text": "\ufb87", "char_type_name": "word", "verse_id": 1912, "verse_number": 11}, {"id": 13333, "position": 2, "line_number": 6, "text": "\ufb88", "char_type_name": "word", "verse_id": 1912, "verse_number": 11}], [{"id": 13334, "position": 3, "line_number": 7, "text": "\ufb89", "char_type_name": "word", "verse_id": 1912, "verse_number": 11}, {"id": 13335, "position": 4, "line_number": 7, "text": "\ufb8a", "char_type_name": "word", "verse_id": 1912, "verse_number": 11}, {"id": 13336, "position": 5, "line_number": 7, "text": "\ufb8b", "char_type_name": "word", "verse_id": 1912, "verse_number": 11}, {"id": 13337, "position": 6, "line_number": 7, "text": "\ufb8c", "char_type_name": "word", "verse_id": 1912, "verse_number": 11}, {"id": 13338, "position": 7, "line_number": 7, "text": "\ufb8d", "char_type_name": "word", "verse_id": 1912, "verse_number": 11}, {"id": 13339, "position": 8, "line_number": 7, "text": "\ufb8e", "char_type_name": "word", "verse_id": 1912, "verse_number": 11}, {"id": 13340, "position": 9, "line_number": 7, "text": "\ufb8f", "char_type_name": "word", "verse_id": 1912, "verse_number": 11}], [{"id": 13341, "position": 10, "line_number": 8, "text": "\ufb90\ufb91", "char_type_name": "word", "verse_id": 1912, "verse_number": 11}, {"id": 13343, "position": 11, "line_number": 8, "text": "\ufb92", "char_type_name": "word", "verse_id": 1912, "verse_number": 11}, {"id": 13344, "position": 12, "line_number": 8, "text": "\ufb93", "char_type_name": "word", "verse_id": 1912, "verse_number": 11}, {"id": 13345, "position": 13, "line_number": 8, "text": "\ufb94", "char_type_name": "word", "verse_id": 1912, "verse_number": 11}, {"id": 13346, "position": 14, "line_number": 8, "text": "\ufb95", "char_type_name": "word", "verse_id": 1912, "verse_number": 11}, {"id": 13347, "position": 15, "line_number": 8, "text": "\ufb96", "char_type_name": "word", "verse_id": 1912, "verse_number": 11}, {"id": 13348, "position": 16, "line_number": 8, "text": "\ufb97", "char_type_name": "word", "verse_id": 1912, "verse_number": 11}, {"id": 13349, "position": 17, "line_number": 8, "text": "\ufb98", "char_type_name": "end", "verse_id": 1912, "verse_number": 11}], [{"id": 14611, "position": 1, "line_number": 9, "text": "\ufb99", "char_type_name": "word", "verse_id": 1913, "verse_number": 12}, {"id": 14612, "position": 2, "line_number": 9, "text": "\ufb9a", "char_type_name": "word", "verse_id": 1913, "verse_number": 12}, {"id": 14613, "position": 3, "line_number": 9, "text": "\ufb9b", "char_type_name": "word", "verse_id": 1913, "verse_number": 12}, {"id": 14614, "position": 4, "line_number": 9, "text": "\ufb9c", "char_type_name": "word", "verse_id": 1913, "verse_number": 12}, {"id": 14615, "position": 5, "line_number": 9, "text": "\ufb9d", "char_type_name": "word", "verse_id": 1913, "verse_number": 12}, {"id": 14616, "position": 6, "line_number": 9, "text": "\ufb9e\ufb9f", "char_type_name": "word", "verse_id": 1913, "verse_number": 12}, {"id": 14618, "position": 7, "line_number": 9, "text": "\ufba0", "char_type_name": "word", "verse_id": 1913, "verse_number": 12}], [{"id": 14619, "position": 8, "line_number": 10, "text": "\ufba1", "char_type_name": "word", "verse_id": 1913, "verse_number": 12}, {"id": 14620, "position": 9, "line_number": 10, "text": "\ufba2\ufba3", "char_type_name": "word", "verse_id": 1913, "verse_number": 12}, {"id": 14622, "position": 10, "line_number": 10, "text": "\ufba4", "char_type_name": "word", "verse_id": 1913, "verse_number": 12}, {"id": 14623, "position": 11, "line_number": 10, "text": "\ufba5", "char_type_name": "word", "verse_id": 1913, "verse_number": 12}, {"id": 14624, "position": 12, "line_number": 10, "text": "\ufba6", "char_type_name": "word", "verse_id": 1913, "verse_number": 12}, {"id": 14625, "position": 13, "line_number": 10, "text": "\ufba7", "char_type_name": "word", "verse_id": 1913, "verse_number": 12}, {"id": 14626, "position": 14, "line_number": 10, "text": "\ufba8", "char_type_name": "word", "verse_id": 1913, "verse_number": 12}, {"id": 14627, "position": 15, "line_number": 10, "text": "\ufba9", "char_type_name": "word", "verse_id": 1913, "verse_number": 12}], [{"id": 14628, "position": 16, "line_number": 11, "text": "\ufbaa", "char_type_name": "end", "verse_id": 1913, "verse_number": 12}, {"id": 15704, "position": 1, "line_number": 11, "text": "\ufbab", "char_type_name": "word", "verse_id": 1914, "verse_number": 13}, {"id": 15705, "position": 2, "line_number": 11, "text": "\ufbac", "char_type_name": "word", "verse_id": 1914, "verse_number": 13}, {"id": 15706, "position": 3, "line_number": 11, "text": "\ufbad", "char_type_name": "word", "verse_id": 1914, "verse_number": 13}, {"id": 15707, "position": 4, "line_number": 11, "text": "\ufbae", "char_type_name": "word", "verse_id": 1914, "verse_number": 13}, {"id": 15708, "position": 5, "line_number": 11, "text": "\ufbaf", "char_type_name": "word", "verse_id": 1914, "verse_number": 13}, {"id": 15709, "position": 6, "line_number": 11, "text": "\ufbb0", "char_type_name": "word", "verse_id": 1914, "verse_number": 13}, {"id": 15710, "position": 7, "line_number": 11, "text": "\ufbb1\ufbd3", "char_type_name": "word", "verse_id": 1914, "verse_number": 13}, {"id": 15712, "position": 8, "line_number": 11, "text": "\ufbd4", "char_type_name": "word", "verse_id": 1914, "verse_number": 13}], [{"id": 15713, "position": 9, "line_number": 12, "text": "\ufbd5", "char_type_name": "word", "verse_id": 1914, "verse_number": 13}, {"id": 15714, "position": 10, "line_number": 12, "text": "\ufbd6", "char_type_name": "word", "verse_id": 1914, "verse_number": 13}, {"id": 15715, "position": 11, "line_number": 12, "text": "\ufbd7", "char_type_name": "word", "verse_id": 1914, "verse_number": 13}, {"id": 15716, "position": 12, "line_number": 12, "text": "\ufbd8", "char_type_name": "word", "verse_id": 1914, "verse_number": 13}, {"id": 15717, "position": 13, "line_number": 12, "text": "\ufbd9", "char_type_name": "word", "verse_id": 1914, "verse_number": 13}, {"id": 15718, "position": 14, "line_number": 12, "text": "\ufbda", "char_type_name": "end", "verse_id": 1914, "verse_number": 13}, {"id": 16760, "position": 1, "line_number": 12, "text": "\ufbdb", "char_type_name": "word", "verse_id": 1915, "verse_number": 14}, {"id": 16761, "position": 2, "line_number": 12, "text": "\ufbdc", "char_type_name": "word", "verse_id": 1915, "verse_number": 14}], [{"id": 16762, "position": 3, "line_number": 13, "text": "\ufbdd", "char_type_name": "word", "verse_id": 1915, "verse_number": 14}, {"id": 16763, "position": 4, "line_number": 13, "text": "\ufbde", "char_type_name": "word", "verse_id": 1915, "verse_number": 14}, {"id": 16764, "position": 5, "line_number": 13, "text": "\ufbdf", "char_type_name": "word", "verse_id": 1915, "verse_number": 14}, {"id": 16765, "position": 6, "line_number": 13, "text": "\ufbe0", "char_type_name": "word", "verse_id": 1915, "verse_number": 14}, {"id": 16766, "position": 7, "line_number": 13, "text": "\ufbe1", "char_type_name": "word", "verse_id": 1915, "verse_number": 14}, {"id": 16767, "position": 8, "line_number": 13, "text": "\ufbe2", "char_type_name": "word", "verse_id": 1915, "verse_number": 14}, {"id": 16768, "position": 9, "line_number": 13, "text": "\ufbe3", "char_type_name": "word", "verse_id": 1915, "verse_number": 14}], [{"id": 16769, "position": 10, "line_number": 14, "text": "\ufbe4", "char_type_name": "word", "verse_id": 1915, "verse_number": 14}, {"id": 16770, "position": 11, "line_number": 14, "text": "\ufbe5", "char_type_name": "word", "verse_id": 1915, "verse_number": 14}, {"id": 16771, "position": 12, "line_number": 14, "text": "\ufbe6", "char_type_name": "word", "verse_id": 1915, "verse_number": 14}, {"id": 16772, "position": 13, "line_number": 14, "text": "\ufbe7", "char_type_name": "word", "verse_id": 1915, "verse_number": 14}, {"id": 16773, "position": 14, "line_number": 14, "text": "\ufbe8", "char_type_name": "word", "verse_id": 1915, "verse_number": 14}, {"id": 16774, "position": 15, "line_number": 14, "text": "\ufbe9", "char_type_name": "word", "verse_id": 1915, "verse_number": 14}, {"id": 16775, "position": 16, "line_number": 14, "text": "\ufbea", "char_type_name": "word", "verse_id": 1915, "verse_number": 14}], [{"id": 16776, "position": 17, "line_number": 15, "text": "\ufbeb", "char_type_name": "word", "verse_id": 1915, "verse_number": 14}, {"id": 16777, "position": 18, "line_number": 15, "text": "\ufbec", "char_type_name": "word", "verse_id": 1915, "verse_number": 14}, {"id": 16778, "position": 19, "line_number": 15, "text": "\ufbed", "char_type_name": "word", "verse_id": 1915, "verse_number": 14}, {"id": 16779, "position": 20, "line_number": 15, "text": "\ufbee", "char_type_name": "word", "verse_id": 1915, "verse_number": 14}, {"id": 16780, "position": 21, "line_number": 15, "text": "\ufbef", "char_type_name": "word", "verse_id": 1915, "verse_number": 14}, {"id": 16781, "position": 22, "line_number": 15, "text": "\ufbf0", "char_type_name": "end", "verse_id": 1915, "verse_number": 14}]]}]}